ricercando/__init__.py
ricercando/connection.py
ricercando/db.py
ricercando/ipython_connector.py
ricercando/queries.py
ricercando/query_base.py
ricercando/significance.py
ricercando/util.py
ricercando/orange_widgets/__init__.py
ricercando/orange_widgets/owipythonconnector.py
ricercando/orange_widgets/owmonroedata.py
ricercando/orange_widgets/owsignificantgroups.py
ricercando/orange_widgets/util.py
ricercando/orange_widgets/icons/IPythonConnector.svg
ricercando/orange_widgets/icons/SignificantGroups.svg
ricercando/orange_widgets/icons/category.svg
ricercando-0.1.4.dist-info/METADATA
ricercando-0.1.4.dist-info/WHEEL
ricercando-0.1.4.dist-info/entry_points.txt
ricercando-0.1.4.dist-info/top_level.txt
ricercando-0.1.4.dist-info/RECORD
