Metadata-Version: 2.1
Name: ricercando
Version: 0.1.4
Summary: Utility library for querying, analyzing, and visualizing MONROE data
Home-page: https://github.com/ivek1312/ricercando
Author: UL FRI, Biolab
Author-email: UNKNOWN
License: UNKNOWN
Keywords: orange3 add-on
Platform: UNKNOWN
Classifier: Framework :: IPython
Classifier: Framework :: Jupyter
Classifier: Programming Language :: Python :: 3 :: Only
Classifier: License :: OSI Approved :: GNU General Public License v3 or later (GPLv3+)
Classifier: Operating System :: OS Independent
Classifier: Topic :: Scientific/Engineering :: Visualization
Classifier: Topic :: Scientific/Engineering :: Information Analysis
Classifier: Topic :: Scientific/Engineering :: Artificial Intelligence
Classifier: Intended Audience :: Science/Research
Requires-Dist: Orange3
Requires-Dist: numpy
Requires-Dist: pandas (>=0.19.0)
Requires-Dist: ipython
Requires-Dist: influxdb
